[{"title":"test post 34","category":"cat2","tags":["tag0","tag1","tag2"],"author":"admin","preview":"jlhkjhkhjkhjk","date":1578318611477},{"title":"test post 32","category":"cat2","tags":["tag0","tag1","tag2"],"author":"admin","preview":"jlhkjhkhjkhjk","date":1578318352505},{"title":"test post 30","category":"cat1","tags":["tag0","tag1","tag2"],"author":"admin2","preview":"hello1","date":1578318280186},{"title":"test post 29","category":"cat1","tags":["tag0","tag1","tag2"],"author":"admin2","preview":"post 29 working","date":1578314693710},{"title":"test post 28","category":"cat2","tags":["tag0","tag1","tag2"],"author":"admin2","preview":"jlhkjhkhjkhjk","date":1578310392381},{"title":"test post 27","category":"cat2","tags":["tag0","tag1","tag2"],"author":"admin2","preview":"jlhkjhkhjkhjk","date":1578307047442},{"title":"test post 26","category":"cat2","tags":["tag0","tag1","tag2"],"author":"admin","preview":"jlhkjhkhjkhjk","date":1578307030515},{"title":"test post 25","category":"cat1","tags":["tag0","tag1","tag2"],"author":"admin","preview":"jlhkjhkhjkhjk","date":1578307015613},{"title":"test post 24","category":"cat1","tags":["tag0","tag1","tag2"],"author":"admin","preview":"jlhkjhkhjkhjk","date":1578306917878},{"title":"test post 23","category":"cat1","tags":["tag0","tag1","tag2"],"author":"admin","preview":"jlhkjhkhjkhjk","date":1578305817175},{"title":"test post 22","category":"cat2","tags":["tag0","tag1","tag2"],"author":"admin2","preview":"jlhkjhkhjkhjk","date":1578305769059},{"title":"test post 21","category":"cat2","tags":["tag0","tag1","tag2"],"author":"admin2","preview":"jlhkjhkhjkhjk","date":1578304937630},{"title":"test post 20","category":"cat1","tags":["tag0","tag1","tag2"],"author":"admin2","preview":"jlhkjhkhjkhjk","date":1578304586131},{"title":"test post 19","category":"cat2","tags":["tag0","tag1","tag2"],"author":"admin","preview":"jlhkjhkhjkhjk","date":1578304302091},{"title":"test post 18","category":"cat2","tags":["tag0","tag1","tag2"],"author":"admin","preview":"jlhkjhkhjkhjk","date":1578304182344},{"title":"test post 17","category":"cat2","tags":["tag0","tag1","tag2"],"author":"admin","preview":"jlhkjhkhjkhjk","date":1578197583555},{"title":"test post 16","category":"cat2","tags":["tag0","tag1","tag2"],"author":"admin","preview":"jlhkjhkhjkhjk","date":1578197091949},{"title":"test post 15","category":"cat2","tags":["tag0","tag1","tag2"],"author":"admin","preview":"jlhkjhkhjkhjk","date":1578196185797},{"title":"test post 14","category":"cat2","tags":["tag0","tag1","tag2"],"author":"admin","preview":"jlhkjhkhjkhjk","date":1578196126621},{"title":"test post 13","category":"cat2","tags":["tag0","tag1","tag2"],"author":"admin","preview":"jlhkjhkhjkhjk","date":1578195690352}]